heiwa4126_hello_python/__about__.py
heiwa4126_hello_python/__init__.py
heiwa4126_hello_python/__main__.py
heiwa4126_hello_python/cli.py
heiwa4126_hello_python/hello.py
heiwa4126_hello_python-0.2.0.dist-info/METADATA
heiwa4126_hello_python-0.2.0.dist-info/WHEEL
heiwa4126_hello_python-0.2.0.dist-info/entry_points.txt
heiwa4126_hello_python-0.2.0.dist-info/licenses/LICENSE
heiwa4126_hello_python-0.2.0.dist-info/RECORD
