Metadata-Version: 2.3
Name: heiwa4126-hello-python
Version: 0.2.0
Summary: An example python project
Project-URL: Documentation, https://github.com/heiwa4126/hello-python#readme
Project-URL: Issues, https://github.com/heiwa4126/hello-python/issues
Project-URL: Source, https://github.com/heiwa4126/hello-python
Author-email: heiwa4126 <heiwa4126@gmail.com>
License-Expression: MIT
License-File: LICENSE
Keywords: demo,helloworld
Classifier: Programming Language :: Python
Classifier: Programming Language :: Python :: 3.8
Classifier: Programming Language :: Python :: 3.9
Classifier: Programming Language :: Python :: 3.10
Classifier: Programming Language :: Python :: 3.11
Classifier: Programming Language :: Python :: 3.12
Classifier: Programming Language :: Python :: Implementation :: CPython
Requires-Python: >=3.8
Requires-Dist: cowsay
